[{"id":1,"first_name":"Tait","age":1},
{"id":2,"first_name":"Haily","age":2},
{"id":3,"first_name":"Gilberto","age":3},
{"id":4,"first_name":"Axel","age":4},
{"id":5,"first_name":"Laurene","age":5},
{"id":6,"first_name":"Eddy","age":6},
{"id":7,"first_name":"Hestia","age":7},
{"id":8,"first_name":"Rollins","age":8},
{"id":9,"first_name":"Cthrine","age":9},
{"id":10,"first_name":"Cristy","age":10},
{"id":11,"first_name":"Rosanna","age":11},
{"id":12,"first_name":"Clayborne","age":12},
{"id":13,"first_name":"Rozina","age":13},
{"id":14,"first_name":"Carma","age":14},
{"id":15,"first_name":"Upton","age":15},
{"id":16,"first_name":"Maisie","age":16},
{"id":17,"first_name":"Barbie","age":17},
{"id":18,"first_name":"Jaquenetta","age":18},
{"id":19,"first_name":"Mellisa","age":19},
{"id":20,"first_name":"Jacob","age":20},
{"id":21,"first_name":"Dorian","age":21},
{"id":22,"first_name":"Sinclair","age":22},
{"id":23,"first_name":"Aggie","age":23},
{"id":24,"first_name":"Audra","age":24},
{"id":25,"first_name":"Devonne","age":25},
{"id":26,"first_name":"Cirilo","age":26},
{"id":27,"first_name":"Al","age":27},
{"id":28,"first_name":"Harmonie","age":28},
{"id":29,"first_name":"Deloris","age":29},
{"id":30,"first_name":"Lanette","age":30},
{"id":31,"first_name":"Euell","age":31},
{"id":32,"first_name":"Fernanda","age":32},
{"id":33,"first_name":"Juliana","age":33},
{"id":34,"first_name":"Jamey","age":34},
{"id":35,"first_name":"Anatol","age":35},
{"id":36,"first_name":"Collette","age":36},
{"id":37,"first_name":"Findley","age":37},
{"id":38,"first_name":"Jayson","age":38},
{"id":39,"first_name":"Radcliffe","age":39},
{"id":40,"first_name":"Bail","age":40},
{"id":41,"first_name":"Inglis","age":41},
{"id":42,"first_name":"Charlena","age":42},
{"id":43,"first_name":"Wilow","age":43},
{"id":44,"first_name":"Jorrie","age":44},
{"id":45,"first_name":"Paxon","age":45},
{"id":46,"first_name":"Shana","age":46},
{"id":47,"first_name":"Dewey","age":47},
{"id":48,"first_name":"Conroy","age":48},
{"id":49,"first_name":"Cherrita","age":49},
{"id":50,"first_name":"Roanne","age":50},
{"id":51,"first_name":"Ferrell","age":51},
{"id":52,"first_name":"Chaddie","age":52},
{"id":53,"first_name":"Nathanil","age":53},
{"id":54,"first_name":"Iosep","age":54},
{"id":55,"first_name":"Consolata","age":55},
{"id":56,"first_name":"Kris","age":56},
{"id":57,"first_name":"Kassey","age":57},
{"id":58,"first_name":"Perry","age":58},
{"id":59,"first_name":"Cordi","age":59},
{"id":60,"first_name":"Laurel","age":60},
{"id":61,"first_name":"Myrtice","age":61},
{"id":62,"first_name":"Ruben","age":62},
{"id":63,"first_name":"Ezmeralda","age":63},
{"id":64,"first_name":"Upton","age":64},
{"id":65,"first_name":"Rochester","age":65},
{"id":66,"first_name":"Vladamir","age":66},
{"id":67,"first_name":"Lanae","age":67},
{"id":68,"first_name":"Hermy","age":68},
{"id":69,"first_name":"Rorke","age":69},
{"id":70,"first_name":"Marilin","age":70},
{"id":71,"first_name":"Moise","age":71},
{"id":72,"first_name":"Roch","age":72},
{"id":73,"first_name":"Billie","age":73},
{"id":74,"first_name":"Torin","age":74},
{"id":75,"first_name":"Maurene","age":75},
{"id":76,"first_name":"Penrod","age":76},
{"id":77,"first_name":"Angelico","age":77},
{"id":78,"first_name":"Elke","age":78},
{"id":79,"first_name":"Egan","age":79},
{"id":80,"first_name":"Peadar","age":80},
{"id":81,"first_name":"Gilly","age":81},
{"id":82,"first_name":"Jeane","age":82},
{"id":83,"first_name":"Alard","age":83},
{"id":84,"first_name":"Geoffrey","age":84},
{"id":85,"first_name":"Matthaeus","age":85},
{"id":86,"first_name":"Hale","age":86},
{"id":87,"first_name":"Jacinda","age":87},
{"id":88,"first_name":"Benedikt","age":88},
{"id":89,"first_name":"Gardener","age":89},
{"id":90,"first_name":"Antonietta","age":90},
{"id":91,"first_name":"Elle","age":91},
{"id":92,"first_name":"Chelsie","age":92},
{"id":93,"first_name":"Winifield","age":93},
{"id":94,"first_name":"Arliene","age":94},
{"id":95,"first_name":"Darline","age":95},
{"id":96,"first_name":"Ethan","age":96},
{"id":97,"first_name":"Ericka","age":97},
{"id":98,"first_name":"Corinne","age":98},
{"id":99,"first_name":"Zerk","age":99},
{"id":100,"first_name":"Cooper","age":100}]